{
    "files": [
        {
            "contentLength": 32,
            "contentType": "application/octet-stream",
            "lastModifiedTime": 1724764618.983847,
            "name": "neoforge-20.6.120-changelog.txt.asc.md5",
            "type": "FILE"
        },
        {
            "contentLength": 40,
            "contentType": "application/octet-stream",
            "lastModifiedTime": 1724764618.599848,
            "name": "neoforge-20.6.120-changelog.txt.asc.sha1",
            "type": "FILE"
        },
        {
            "contentLength": 64,
            "contentType": "application/octet-stream",
            "lastModifiedTime": 1724764619.195847,
            "name": "neoforge-20.6.120-changelog.txt.asc.sha256",
            "type": "FILE"
        },
        {
            "contentLength": 128,
            "contentType": "application/octet-stream",
            "lastModifiedTime": 1724764619.403847,
            "name": "neoforge-20.6.120-changelog.txt.asc.sha512",
            "type": "FILE"
        },
        {
            "contentLength": 215,
            "contentType": "application/octet-stream",
            "lastModifiedTime": 1724764618.399848,
            "name": "neoforge-20.6.120-changelog.txt.asc",
            "type": "FILE"
        },
        {
            "contentLength": 32,
            "contentType": "application/octet-stream",
            "lastModifiedTime": 1724764609.799851,
            "name": "neoforge-20.6.120-changelog.txt.md5",
            "type": "FILE"
        },
        {
            "contentLength": 40,
            "contentType": "application/octet-stream",
            "lastModifiedTime": 1724764609.587851,
            "name": "neoforge-20.6.120-changelog.txt.sha1",
            "type": "FILE"
        },
        {
            "contentLength": 64,
            "contentType": "application/octet-stream",
            "lastModifiedTime": 1724764610.003851,
            "name": "neoforge-20.6.120-changelog.txt.sha256",
            "type": "FILE"
        },
        {
            "contentLength": 128,
            "contentType": "application/octet-stream",
            "lastModifiedTime": 1724764610.203851,
            "name": "neoforge-20.6.120-changelog.txt.sha512",
            "type": "FILE"
        },
        {
            "contentLength": 10642,
            "contentType": "text/plain",
            "lastModifiedTime": 1724764609.047851,
            "name": "neoforge-20.6.120-changelog.txt",
            "type": "FILE"
        },
        {
            "contentLength": 32,
            "contentType": "application/octet-stream",
            "lastModifiedTime": 1724764617.583848,
            "name": "neoforge-20.6.120-installer.jar.asc.md5",
            "type": "FILE"
        },
        {
            "contentLength": 40,
            "contentType": "application/octet-stream",
            "lastModifiedTime": 1724764617.375848,
            "name": "neoforge-20.6.120-installer.jar.asc.sha1",
            "type": "FILE"
        },
        {
            "contentLength": 64,
            "contentType": "application/octet-stream",
            "lastModifiedTime": 1724764617.803848,
            "name": "neoforge-20.6.120-installer.jar.asc.sha256",
            "type": "FILE"
        },
        {
            "contentLength": 128,
            "contentType": "application/octet-stream",
            "lastModifiedTime": 1724764618.191848,
            "name": "neoforge-20.6.120-installer.jar.asc.sha512",
            "type": "FILE"
        },
        {
            "contentLength": 215,
            "contentType": "application/octet-stream",
            "lastModifiedTime": 1724764616.987848,
            "name": "neoforge-20.6.120-installer.jar.asc",
            "type": "FILE"
        },
        {
            "contentLength": 32,
            "contentType": "application/octet-stream",
            "lastModifiedTime": 1724764605.683852,
            "name": "neoforge-20.6.120-installer.jar.md5",
            "type": "FILE"
        },
        {
            "contentLength": 40,
            "contentType": "application/octet-stream",
            "lastModifiedTime": 1724764605.403852,
            "name": "neoforge-20.6.120-installer.jar.sha1",
            "type": "FILE"
        },
        {
            "contentLength": 64,
            "contentType": "application/octet-stream",
            "lastModifiedTime": 1724764606.075852,
            "name": "neoforge-20.6.120-installer.jar.sha256",
            "type": "FILE"
        },
        {
            "contentLength": 128,
            "contentType": "application/octet-stream",
            "lastModifiedTime": 1724764606.295852,
            "name": "neoforge-20.6.120-installer.jar.sha512",
            "type": "FILE"
        },
        {
            "contentLength": 6647554,
            "contentType": "application/java-archive",
            "lastModifiedTime": 1724764604.983853,
            "name": "neoforge-20.6.120-installer.jar",
            "type": "FILE"
        },
        {
            "contentLength": 32,
            "contentType": "application/octet-stream",
            "lastModifiedTime": 1724764612.78785,
            "name": "neoforge-20.6.120.pom.asc.md5",
            "type": "FILE"
        },
        {
            "contentLength": 40,
            "contentType": "application/octet-stream",
            "lastModifiedTime": 1724764612.56385,
            "name": "neoforge-20.6.120.pom.asc.sha1",
            "type": "FILE"
        },
        {
            "contentLength": 64,
            "contentType": "application/octet-stream",
            "lastModifiedTime": 1724764612.99985,
            "name": "neoforge-20.6.120.pom.asc.sha256",
            "type": "FILE"
        },
        {
            "contentLength": 128,
            "contentType": "application/octet-stream",
            "lastModifiedTime": 1724764613.387849,
            "name": "neoforge-20.6.120.pom.asc.sha512",
            "type": "FILE"
        },
        {
            "contentLength": 215,
            "contentType": "application/octet-stream",
            "lastModifiedTime": 1724764612.15985,
            "name": "neoforge-20.6.120.pom.asc",
            "type": "FILE"
        },
        {
            "contentLength": 32,
            "contentType": "application/octet-stream",
            "lastModifiedTime": 1724764603.063853,
            "name": "neoforge-20.6.120.pom.md5",
            "type": "FILE"
        },
        {
            "contentLength": 40,
            "contentType": "application/octet-stream",
            "lastModifiedTime": 1724764602.683853,
            "name": "neoforge-20.6.120.pom.sha1",
            "type": "FILE"
        },
        {
            "contentLength": 64,
            "contentType": "application/octet-stream",
            "lastModifiedTime": 1724764603.447853,
            "name": "neoforge-20.6.120.pom.sha256",
            "type": "FILE"
        },
        {
            "contentLength": 128,
            "contentType": "application/octet-stream",
            "lastModifiedTime": 1724764603.667853,
            "name": "neoforge-20.6.120.pom.sha512",
            "type": "FILE"
        },
        {
            "contentLength": 17612,
            "contentType": "application/xml",
            "lastModifiedTime": 1724764602.283854,
            "name": "neoforge-20.6.120.pom",
            "type": "FILE"
        },
        {
            "contentLength": 32,
            "contentType": "application/octet-stream",
            "lastModifiedTime": 1724764614.395849,
            "name": "neoforge-20.6.120-sources.jar.asc.md5",
            "type": "FILE"
        },
        {
            "contentLength": 40,
            "contentType": "application/octet-stream",
            "lastModifiedTime": 1724764614.007849,
            "name": "neoforge-20.6.120-sources.jar.asc.sha1",
            "type": "FILE"
        },
        {
            "contentLength": 64,
            "contentType": "application/octet-stream",
            "lastModifiedTime": 1724764614.607849,
            "name": "neoforge-20.6.120-sources.jar.asc.sha256",
            "type": "FILE"
        },
        {
            "contentLength": 128,
            "contentType": "application/octet-stream",
            "lastModifiedTime": 1724764614.999849,
            "name": "neoforge-20.6.120-sources.jar.asc.sha512",
            "type": "FILE"
        },
        {
            "contentLength": 215,
            "contentType": "application/octet-stream",
            "lastModifiedTime": 1724764613.615849,
            "name": "neoforge-20.6.120-sources.jar.asc",
            "type": "FILE"
        },
        {
            "contentLength": 32,
            "contentType": "application/octet-stream",
            "lastModifiedTime": 1724764608.179851,
            "name": "neoforge-20.6.120-sources.jar.md5",
            "type": "FILE"
        },
        {
            "contentLength": 40,
            "contentType": "application/octet-stream",
            "lastModifiedTime": 1724764607.815852,
            "name": "neoforge-20.6.120-sources.jar.sha1",
            "type": "FILE"
        },
        {
            "contentLength": 64,
            "contentType": "application/octet-stream",
            "lastModifiedTime": 1724764608.567851,
            "name": "neoforge-20.6.120-sources.jar.sha256",
            "type": "FILE"
        },
        {
            "contentLength": 128,
            "contentType": "application/octet-stream",
            "lastModifiedTime": 1724764608.783851,
            "name": "neoforge-20.6.120-sources.jar.sha512",
            "type": "FILE"
        },
        {
            "contentLength": 1560334,
            "contentType": "application/java-archive",
            "lastModifiedTime": 1724764607.427852,
            "name": "neoforge-20.6.120-sources.jar",
            "type": "FILE"
        },
        {
            "contentLength": 32,
            "contentType": "application/octet-stream",
            "lastModifiedTime": 1724764611.19585,
            "name": "neoforge-20.6.120-universal.jar.asc.md5",
            "type": "FILE"
        },
        {
            "contentLength": 40,
            "contentType": "application/octet-stream",
            "lastModifiedTime": 1724764610.82385,
            "name": "neoforge-20.6.120-universal.jar.asc.sha1",
            "type": "FILE"
        },
        {
            "contentLength": 64,
            "contentType": "application/octet-stream",
            "lastModifiedTime": 1724764611.57985,
            "name": "neoforge-20.6.120-universal.jar.asc.sha256",
            "type": "FILE"
        },
        {
            "contentLength": 128,
            "contentType": "application/octet-stream",
            "lastModifiedTime": 1724764611.95585,
            "name": "neoforge-20.6.120-universal.jar.asc.sha512",
            "type": "FILE"
        },
        {
            "contentLength": 215,
            "contentType": "application/octet-stream",
            "lastModifiedTime": 1724764610.591851,
            "name": "neoforge-20.6.120-universal.jar.asc",
            "type": "FILE"
        },
        {
            "contentLength": 32,
            "contentType": "application/octet-stream",
            "lastModifiedTime": 1724764621.467846,
            "name": "neoforge-20.6.120-universal.jar.md5",
            "type": "FILE"
        },
        {
            "contentLength": 40,
            "contentType": "application/octet-stream",
            "lastModifiedTime": 1724764621.071847,
            "name": "neoforge-20.6.120-universal.jar.sha1",
            "type": "FILE"
        },
        {
            "contentLength": 64,
            "contentType": "application/octet-stream",
            "lastModifiedTime": 1724764621.947846,
            "name": "neoforge-20.6.120-universal.jar.sha256",
            "type": "FILE"
        },
        {
            "contentLength": 128,
            "contentType": "application/octet-stream",
            "lastModifiedTime": 1724764622.367846,
            "name": "neoforge-20.6.120-universal.jar.sha512",
            "type": "FILE"
        },
        {
            "contentLength": 2685337,
            "contentType": "application/java-archive",
            "lastModifiedTime": 1724764620.667847,
            "name": "neoforge-20.6.120-universal.jar",
            "type": "FILE"
        },
        {
            "contentLength": 32,
            "contentType": "application/octet-stream",
            "lastModifiedTime": 1724764615.979849,
            "name": "neoforge-20.6.120-userdev.jar.asc.md5",
            "type": "FILE"
        },
        {
            "contentLength": 40,
            "contentType": "application/octet-stream",
            "lastModifiedTime": 1724764615.767849,
            "name": "neoforge-20.6.120-userdev.jar.asc.sha1",
            "type": "FILE"
        },
        {
            "contentLength": 64,
            "contentType": "application/octet-stream",
            "lastModifiedTime": 1724764616.359848,
            "name": "neoforge-20.6.120-userdev.jar.asc.sha256",
            "type": "FILE"
        },
        {
            "contentLength": 128,
            "contentType": "application/octet-stream",
            "lastModifiedTime": 1724764616.603848,
            "name": "neoforge-20.6.120-userdev.jar.asc.sha512",
            "type": "FILE"
        },
        {
            "contentLength": 215,
            "contentType": "application/octet-stream",
            "lastModifiedTime": 1724764615.215849,
            "name": "neoforge-20.6.120-userdev.jar.asc",
            "type": "FILE"
        },
        {
            "contentLength": 32,
            "contentType": "application/octet-stream",
            "lastModifiedTime": 1724764624.979845,
            "name": "neoforge-20.6.120-userdev.jar.md5",
            "type": "FILE"
        },
        {
            "contentLength": 40,
            "contentType": "application/octet-stream",
            "lastModifiedTime": 1724764624.739845,
            "name": "neoforge-20.6.120-userdev.jar.sha1",
            "type": "FILE"
        },
        {
            "contentLength": 64,
            "contentType": "application/octet-stream",
            "lastModifiedTime": 1724764625.375845,
            "name": "neoforge-20.6.120-userdev.jar.sha256",
            "type": "FILE"
        },
        {
            "contentLength": 128,
            "contentType": "application/octet-stream",
            "lastModifiedTime": 1724764625.599845,
            "name": "neoforge-20.6.120-userdev.jar.sha512",
            "type": "FILE"
        },
        {
            "contentLength": 3273912,
            "contentType": "application/java-archive",
            "lastModifiedTime": 1724764624.343845,
            "name": "neoforge-20.6.120-userdev.jar",
            "type": "FILE"
        }
    ],
    "name": "20.6.120",
    "type": "DIRECTORY"
}