{
    "files": [
        {
            "contentLength": 32,
            "contentType": "application/octet-stream",
            "lastModifiedTime": 1737659697.351276,
            "name": "neoforge-21.4.74-beta-changelog.txt.asc.md5",
            "type": "FILE"
        },
        {
            "contentLength": 40,
            "contentType": "application/octet-stream",
            "lastModifiedTime": 1737659696.915276,
            "name": "neoforge-21.4.74-beta-changelog.txt.asc.sha1",
            "type": "FILE"
        },
        {
            "contentLength": 64,
            "contentType": "application/octet-stream",
            "lastModifiedTime": 1737659697.803276,
            "name": "neoforge-21.4.74-beta-changelog.txt.asc.sha256",
            "type": "FILE"
        },
        {
            "contentLength": 128,
            "contentType": "application/octet-stream",
            "lastModifiedTime": 1737659698.275276,
            "name": "neoforge-21.4.74-beta-changelog.txt.asc.sha512",
            "type": "FILE"
        },
        {
            "contentLength": 225,
            "contentType": "application/octet-stream",
            "lastModifiedTime": 1737659696.455276,
            "name": "neoforge-21.4.74-beta-changelog.txt.asc",
            "type": "FILE"
        },
        {
            "contentLength": 32,
            "contentType": "application/octet-stream",
            "lastModifiedTime": 1737659701.987277,
            "name": "neoforge-21.4.74-beta-changelog.txt.md5",
            "type": "FILE"
        },
        {
            "contentLength": 40,
            "contentType": "application/octet-stream",
            "lastModifiedTime": 1737659701.515277,
            "name": "neoforge-21.4.74-beta-changelog.txt.sha1",
            "type": "FILE"
        },
        {
            "contentLength": 64,
            "contentType": "application/octet-stream",
            "lastModifiedTime": 1737659702.463277,
            "name": "neoforge-21.4.74-beta-changelog.txt.sha256",
            "type": "FILE"
        },
        {
            "contentLength": 128,
            "contentType": "application/octet-stream",
            "lastModifiedTime": 1737659702.915277,
            "name": "neoforge-21.4.74-beta-changelog.txt.sha512",
            "type": "FILE"
        },
        {
            "contentLength": 12244,
            "contentType": "text/plain",
            "lastModifiedTime": 1737659701.059277,
            "name": "neoforge-21.4.74-beta-changelog.txt",
            "type": "FILE"
        },
        {
            "contentLength": 32,
            "contentType": "application/octet-stream",
            "lastModifiedTime": 1737659695.087276,
            "name": "neoforge-21.4.74-beta-installer.jar.asc.md5",
            "type": "FILE"
        },
        {
            "contentLength": 40,
            "contentType": "application/octet-stream",
            "lastModifiedTime": 1737659694.623275,
            "name": "neoforge-21.4.74-beta-installer.jar.asc.sha1",
            "type": "FILE"
        },
        {
            "contentLength": 64,
            "contentType": "application/octet-stream",
            "lastModifiedTime": 1737659695.535276,
            "name": "neoforge-21.4.74-beta-installer.jar.asc.sha256",
            "type": "FILE"
        },
        {
            "contentLength": 128,
            "contentType": "application/octet-stream",
            "lastModifiedTime": 1737659695.987276,
            "name": "neoforge-21.4.74-beta-installer.jar.asc.sha512",
            "type": "FILE"
        },
        {
            "contentLength": 225,
            "contentType": "application/octet-stream",
            "lastModifiedTime": 1737659694.175275,
            "name": "neoforge-21.4.74-beta-installer.jar.asc",
            "type": "FILE"
        },
        {
            "contentLength": 32,
            "contentType": "application/octet-stream",
            "lastModifiedTime": 1737659730.467283,
            "name": "neoforge-21.4.74-beta-installer.jar.md5",
            "type": "FILE"
        },
        {
            "contentLength": 40,
            "contentType": "application/octet-stream",
            "lastModifiedTime": 1737659730.011283,
            "name": "neoforge-21.4.74-beta-installer.jar.sha1",
            "type": "FILE"
        },
        {
            "contentLength": 64,
            "contentType": "application/octet-stream",
            "lastModifiedTime": 1737659730.963283,
            "name": "neoforge-21.4.74-beta-installer.jar.sha256",
            "type": "FILE"
        },
        {
            "contentLength": 128,
            "contentType": "application/octet-stream",
            "lastModifiedTime": 1737659731.451283,
            "name": "neoforge-21.4.74-beta-installer.jar.sha512",
            "type": "FILE"
        },
        {
            "contentLength": 7153433,
            "contentType": "application/java-archive",
            "lastModifiedTime": 1737659729.523283,
            "name": "neoforge-21.4.74-beta-installer.jar",
            "type": "FILE"
        },
        {
            "contentLength": 32,
            "contentType": "application/octet-stream",
            "lastModifiedTime": 1737659718.363281,
            "name": "neoforge-21.4.74-beta-moddev-config.json.asc.md5",
            "type": "FILE"
        },
        {
            "contentLength": 40,
            "contentType": "application/octet-stream",
            "lastModifiedTime": 1737659717.91528,
            "name": "neoforge-21.4.74-beta-moddev-config.json.asc.sha1",
            "type": "FILE"
        },
        {
            "contentLength": 64,
            "contentType": "application/octet-stream",
            "lastModifiedTime": 1737659718.811281,
            "name": "neoforge-21.4.74-beta-moddev-config.json.asc.sha256",
            "type": "FILE"
        },
        {
            "contentLength": 128,
            "contentType": "application/octet-stream",
            "lastModifiedTime": 1737659719.271281,
            "name": "neoforge-21.4.74-beta-moddev-config.json.asc.sha512",
            "type": "FILE"
        },
        {
            "contentLength": 225,
            "contentType": "application/octet-stream",
            "lastModifiedTime": 1737659717.44728,
            "name": "neoforge-21.4.74-beta-moddev-config.json.asc",
            "type": "FILE"
        },
        {
            "contentLength": 32,
            "contentType": "application/octet-stream",
            "lastModifiedTime": 1737659689.235274,
            "name": "neoforge-21.4.74-beta-moddev-config.json.md5",
            "type": "FILE"
        },
        {
            "contentLength": 40,
            "contentType": "application/octet-stream",
            "lastModifiedTime": 1737659688.767274,
            "name": "neoforge-21.4.74-beta-moddev-config.json.sha1",
            "type": "FILE"
        },
        {
            "contentLength": 64,
            "contentType": "application/octet-stream",
            "lastModifiedTime": 1737659689.683274,
            "name": "neoforge-21.4.74-beta-moddev-config.json.sha256",
            "type": "FILE"
        },
        {
            "contentLength": 128,
            "contentType": "application/octet-stream",
            "lastModifiedTime": 1737659690.135274,
            "name": "neoforge-21.4.74-beta-moddev-config.json.sha512",
            "type": "FILE"
        },
        {
            "contentLength": 11589,
            "contentType": "application/json",
            "lastModifiedTime": 1737659688.311274,
            "name": "neoforge-21.4.74-beta-moddev-config.json",
            "type": "FILE"
        },
        {
            "contentLength": 32,
            "contentType": "application/octet-stream",
            "lastModifiedTime": 1737659714.12328,
            "name": "neoforge-21.4.74-beta.module.asc.md5",
            "type": "FILE"
        },
        {
            "contentLength": 40,
            "contentType": "application/octet-stream",
            "lastModifiedTime": 1737659713.66728,
            "name": "neoforge-21.4.74-beta.module.asc.sha1",
            "type": "FILE"
        },
        {
            "contentLength": 64,
            "contentType": "application/octet-stream",
            "lastModifiedTime": 1737659714.56328,
            "name": "neoforge-21.4.74-beta.module.asc.sha256",
            "type": "FILE"
        },
        {
            "contentLength": 128,
            "contentType": "application/octet-stream",
            "lastModifiedTime": 1737659715.01128,
            "name": "neoforge-21.4.74-beta.module.asc.sha512",
            "type": "FILE"
        },
        {
            "contentLength": 225,
            "contentType": "application/octet-stream",
            "lastModifiedTime": 1737659713.219279,
            "name": "neoforge-21.4.74-beta.module.asc",
            "type": "FILE"
        },
        {
            "contentLength": 32,
            "contentType": "application/octet-stream",
            "lastModifiedTime": 1737659699.783277,
            "name": "neoforge-21.4.74-beta.module.md5",
            "type": "FILE"
        },
        {
            "contentLength": 40,
            "contentType": "application/octet-stream",
            "lastModifiedTime": 1737659699.319277,
            "name": "neoforge-21.4.74-beta.module.sha1",
            "type": "FILE"
        },
        {
            "contentLength": 64,
            "contentType": "application/octet-stream",
            "lastModifiedTime": 1737659700.231277,
            "name": "neoforge-21.4.74-beta.module.sha256",
            "type": "FILE"
        },
        {
            "contentLength": 128,
            "contentType": "application/octet-stream",
            "lastModifiedTime": 1737659700.687277,
            "name": "neoforge-21.4.74-beta.module.sha512",
            "type": "FILE"
        },
        {
            "contentLength": 20245,
            "contentType": "application/octet-stream",
            "lastModifiedTime": 1737659698.863276,
            "name": "neoforge-21.4.74-beta.module",
            "type": "FILE"
        },
        {
            "contentLength": 32,
            "contentType": "application/octet-stream",
            "lastModifiedTime": 1737659716.22328,
            "name": "neoforge-21.4.74-beta.pom.asc.md5",
            "type": "FILE"
        },
        {
            "contentLength": 40,
            "contentType": "application/octet-stream",
            "lastModifiedTime": 1737659715.93528,
            "name": "neoforge-21.4.74-beta.pom.asc.sha1",
            "type": "FILE"
        },
        {
            "contentLength": 64,
            "contentType": "application/octet-stream",
            "lastModifiedTime": 1737659716.68728,
            "name": "neoforge-21.4.74-beta.pom.asc.sha256",
            "type": "FILE"
        },
        {
            "contentLength": 128,
            "contentType": "application/octet-stream",
            "lastModifiedTime": 1737659717.14328,
            "name": "neoforge-21.4.74-beta.pom.asc.sha512",
            "type": "FILE"
        },
        {
            "contentLength": 225,
            "contentType": "application/octet-stream",
            "lastModifiedTime": 1737659715.47128,
            "name": "neoforge-21.4.74-beta.pom.asc",
            "type": "FILE"
        },
        {
            "contentLength": 32,
            "contentType": "application/octet-stream",
            "lastModifiedTime": 1737659687.023274,
            "name": "neoforge-21.4.74-beta.pom.md5",
            "type": "FILE"
        },
        {
            "contentLength": 40,
            "contentType": "application/octet-stream",
            "lastModifiedTime": 1737659686.563274,
            "name": "neoforge-21.4.74-beta.pom.sha1",
            "type": "FILE"
        },
        {
            "contentLength": 64,
            "contentType": "application/octet-stream",
            "lastModifiedTime": 1737659687.471274,
            "name": "neoforge-21.4.74-beta.pom.sha256",
            "type": "FILE"
        },
        {
            "contentLength": 128,
            "contentType": "application/octet-stream",
            "lastModifiedTime": 1737659687.947274,
            "name": "neoforge-21.4.74-beta.pom.sha512",
            "type": "FILE"
        },
        {
            "contentLength": 7583,
            "contentType": "application/xml",
            "lastModifiedTime": 1737659686.099274,
            "name": "neoforge-21.4.74-beta.pom",
            "type": "FILE"
        },
        {
            "contentLength": 32,
            "contentType": "application/octet-stream",
            "lastModifiedTime": 1737659735.235284,
            "name": "neoforge-21.4.74-beta-sources.jar.asc.md5",
            "type": "FILE"
        },
        {
            "contentLength": 40,
            "contentType": "application/octet-stream",
            "lastModifiedTime": 1737659734.771284,
            "name": "neoforge-21.4.74-beta-sources.jar.asc.sha1",
            "type": "FILE"
        },
        {
            "contentLength": 64,
            "contentType": "application/octet-stream",
            "lastModifiedTime": 1737659735.771284,
            "name": "neoforge-21.4.74-beta-sources.jar.asc.sha256",
            "type": "FILE"
        },
        {
            "contentLength": 128,
            "contentType": "application/octet-stream",
            "lastModifiedTime": 1737659736.327284,
            "name": "neoforge-21.4.74-beta-sources.jar.asc.sha512",
            "type": "FILE"
        },
        {
            "contentLength": 225,
            "contentType": "application/octet-stream",
            "lastModifiedTime": 1737659734.315284,
            "name": "neoforge-21.4.74-beta-sources.jar.asc",
            "type": "FILE"
        },
        {
            "contentLength": 32,
            "contentType": "application/octet-stream",
            "lastModifiedTime": 1737659692.811275,
            "name": "neoforge-21.4.74-beta-sources.jar.md5",
            "type": "FILE"
        },
        {
            "contentLength": 40,
            "contentType": "application/octet-stream",
            "lastModifiedTime": 1737659692.351275,
            "name": "neoforge-21.4.74-beta-sources.jar.sha1",
            "type": "FILE"
        },
        {
            "contentLength": 64,
            "contentType": "application/octet-stream",
            "lastModifiedTime": 1737659693.259275,
            "name": "neoforge-21.4.74-beta-sources.jar.sha256",
            "type": "FILE"
        },
        {
            "contentLength": 128,
            "contentType": "application/octet-stream",
            "lastModifiedTime": 1737659693.703275,
            "name": "neoforge-21.4.74-beta-sources.jar.sha512",
            "type": "FILE"
        },
        {
            "contentLength": 1785122,
            "contentType": "application/java-archive",
            "lastModifiedTime": 1737659691.891275,
            "name": "neoforge-21.4.74-beta-sources.jar",
            "type": "FILE"
        },
        {
            "contentLength": 32,
            "contentType": "application/octet-stream",
            "lastModifiedTime": 1737659704.291278,
            "name": "neoforge-21.4.74-beta-universal.jar.asc.md5",
            "type": "FILE"
        },
        {
            "contentLength": 40,
            "contentType": "application/octet-stream",
            "lastModifiedTime": 1737659703.831277,
            "name": "neoforge-21.4.74-beta-universal.jar.asc.sha1",
            "type": "FILE"
        },
        {
            "contentLength": 64,
            "contentType": "application/octet-stream",
            "lastModifiedTime": 1737659704.751278,
            "name": "neoforge-21.4.74-beta-universal.jar.asc.sha256",
            "type": "FILE"
        },
        {
            "contentLength": 128,
            "contentType": "application/octet-stream",
            "lastModifiedTime": 1737659705.195278,
            "name": "neoforge-21.4.74-beta-universal.jar.asc.sha512",
            "type": "FILE"
        },
        {
            "contentLength": 225,
            "contentType": "application/octet-stream",
            "lastModifiedTime": 1737659703.363277,
            "name": "neoforge-21.4.74-beta-universal.jar.asc",
            "type": "FILE"
        },
        {
            "contentLength": 32,
            "contentType": "application/octet-stream",
            "lastModifiedTime": 1737659707.967278,
            "name": "neoforge-21.4.74-beta-universal.jar.md5",
            "type": "FILE"
        },
        {
            "contentLength": 40,
            "contentType": "application/octet-stream",
            "lastModifiedTime": 1737659707.475278,
            "name": "neoforge-21.4.74-beta-universal.jar.sha1",
            "type": "FILE"
        },
        {
            "contentLength": 64,
            "contentType": "application/octet-stream",
            "lastModifiedTime": 1737659708.419278,
            "name": "neoforge-21.4.74-beta-universal.jar.sha256",
            "type": "FILE"
        },
        {
            "contentLength": 128,
            "contentType": "application/octet-stream",
            "lastModifiedTime": 1737659708.867279,
            "name": "neoforge-21.4.74-beta-universal.jar.sha512",
            "type": "FILE"
        },
        {
            "contentLength": 3011205,
            "contentType": "application/java-archive",
            "lastModifiedTime": 1737659707.007278,
            "name": "neoforge-21.4.74-beta-universal.jar",
            "type": "FILE"
        },
        {
            "contentLength": 32,
            "contentType": "application/octet-stream",
            "lastModifiedTime": 1737659732.899284,
            "name": "neoforge-21.4.74-beta-userdev.jar.asc.md5",
            "type": "FILE"
        },
        {
            "contentLength": 40,
            "contentType": "application/octet-stream",
            "lastModifiedTime": 1737659732.439283,
            "name": "neoforge-21.4.74-beta-userdev.jar.asc.sha1",
            "type": "FILE"
        },
        {
            "contentLength": 64,
            "contentType": "application/octet-stream",
            "lastModifiedTime": 1737659733.415284,
            "name": "neoforge-21.4.74-beta-userdev.jar.asc.sha256",
            "type": "FILE"
        },
        {
            "contentLength": 128,
            "contentType": "application/octet-stream",
            "lastModifiedTime": 1737659733.859284,
            "name": "neoforge-21.4.74-beta-userdev.jar.asc.sha512",
            "type": "FILE"
        },
        {
            "contentLength": 225,
            "contentType": "application/octet-stream",
            "lastModifiedTime": 1737659731.983283,
            "name": "neoforge-21.4.74-beta-userdev.jar.asc",
            "type": "FILE"
        },
        {
            "contentLength": 32,
            "contentType": "application/octet-stream",
            "lastModifiedTime": 1737659711.795279,
            "name": "neoforge-21.4.74-beta-userdev.jar.md5",
            "type": "FILE"
        },
        {
            "contentLength": 40,
            "contentType": "application/octet-stream",
            "lastModifiedTime": 1737659711.351279,
            "name": "neoforge-21.4.74-beta-userdev.jar.sha1",
            "type": "FILE"
        },
        {
            "contentLength": 64,
            "contentType": "application/octet-stream",
            "lastModifiedTime": 1737659712.303279,
            "name": "neoforge-21.4.74-beta-userdev.jar.sha256",
            "type": "FILE"
        },
        {
            "contentLength": 128,
            "contentType": "application/octet-stream",
            "lastModifiedTime": 1737659712.767279,
            "name": "neoforge-21.4.74-beta-userdev.jar.sha512",
            "type": "FILE"
        },
        {
            "contentLength": 4068451,
            "contentType": "application/java-archive",
            "lastModifiedTime": 1737659710.871279,
            "name": "neoforge-21.4.74-beta-userdev.jar",
            "type": "FILE"
        }
    ],
    "name": "21.4.74-beta",
    "type": "DIRECTORY"
}